buskin/__init__.py
buskin/config.py
buskin/core.py
buskin/entities.py
buskin/utils.py
buskin-0.1.1.dist-info/LICENSE.md
buskin-0.1.1.dist-info/METADATA
buskin-0.1.1.dist-info/WHEEL
buskin-0.1.1.dist-info/top_level.txt
buskin-0.1.1.dist-info/RECORD
