Metadata-Version: 2.1
Name: buskin
Version: 0.1.1
Summary: Analyze characters in fictional texts.
Home-page: https://github.com/nuwandavek/buskin
Author: Vivek Aithal
Author-email: vivekaithal44@gmail.com
License: MIT
Platform: UNKNOWN
Classifier: License :: OSI Approved :: MIT License
Classifier: Programming Language :: Python
Classifier: Programming Language :: Python :: 3
Classifier: Programming Language :: Python :: 3.6
Classifier: Programming Language :: Python :: Implementation :: CPython
Classifier: Programming Language :: Python :: Implementation :: PyPy
Requires-Python: >=3.6.0
Requires-Dist: spacy (==2.1.0)
Requires-Dist: transformers (>=3.3.0)
Requires-Dist: numpy
Requires-Dist: fuzzywuzzy (>=0.18.0)
Requires-Dist: neuralcoref (>=4.0.0)
